crystaldiskmark_parser/__init__.py
crystaldiskmark_parser/parser.py
crystaldiskmark_parser-1.0.4.dist-info/LICENSE
crystaldiskmark_parser-1.0.4.dist-info/METADATA
crystaldiskmark_parser-1.0.4.dist-info/WHEEL
crystaldiskmark_parser-1.0.4.dist-info/top_level.txt
crystaldiskmark_parser-1.0.4.dist-info/RECORD
