Metadata-Version: 2.1
Name: crystaldiskmark-parser
Version: 1.0.4
Summary: Read in the .txt files generated by CrystalDiskMark in Python
Home-page: https://github.com/soerenmetje/CrystalDiskMark-Parser
Author: Soeren Metje
Keywords: python,parser,benchmark,crystaldiskmark7,crystaldiskmark8
Classifier: Intended Audience :: Developers
Classifier: Programming Language :: Python :: 3
Classifier: Operating System :: OS Independent
License-File: LICENSE
Requires-Dist: pandas
